tdsr/__init__.py
tdsr/mac.py
tdsr/speechdispatcher.py
tdsr/tdsr.cfg.dist
tdsr2-0.2.1.dist-info/LICENSE
tdsr2-0.2.1.dist-info/METADATA
tdsr2-0.2.1.dist-info/WHEEL
tdsr2-0.2.1.dist-info/entry_points.txt
tdsr2-0.2.1.dist-info/RECORD
