Metadata-Version: 2.1
Name: tdsr2
Version: 0.2.1
Summary: a fork of Tyler Spivey's tdsr with some minor maintainability improvements from community members
Home-page: http://github.com/jessebot/tdsr
License: GPL-3.0
Keywords: tts,screenreader
Author: Tyler Spivey
Author-email: tspivey@pcdesk.net
Maintainer: jessebot
Maintainer-email: jessebot@linux.com
Classifier: Development Status :: 3 - Alpha
Classifier: License :: OSI Approved :: GNU General Public License v3 (GPLv3)
Classifier: Operating System :: MacOS :: MacOS X
Classifier: Operating System :: POSIX :: Linux
Classifier: Programming Language :: Python :: 2
Classifier: Programming Language :: Python :: 2.7
Classifier: Programming Language :: Python :: 3
Classifier: Programming Language :: Python :: 3.4
Classifier: Programming Language :: Python :: 3.5
Classifier: Programming Language :: Python :: 3.6
Classifier: Programming Language :: Python :: 3.7
Classifier: Programming Language :: Python :: 3.8
Classifier: Programming Language :: Python :: 3.9
Classifier: Programming Language :: Python :: 3.10
Classifier: Programming Language :: Python :: 3.11
Classifier: Programming Language :: Python :: 3.12
Provides-Extra: macos
Project-URL: Bug Tracker, http://github.com/jessebot/tdsr/issues
Project-URL: Documentation, https://github.com/jessebot/tdsr
Project-URL: Repository, http://github.com/jessebot/tdsr
